setup.py
servo/_init_.py
servo.egg-info/PKG-INFO
servo.egg-info/SOURCES.txt
servo.egg-info/dependency_links.txt
servo.egg-info/not-zip-safe
servo.egg-info/top_level.txt