Metadata-Version: 1.0
Name: servo
Version: 1
Summary: Servo Motors Control
Home-page: UNKNOWN
Author: UNKNOWN
Author-email: UNKNOWN
License: ENDAVA
Platform: UNKNOWN
